{"subtopico":["DEMOGR"],"output_name":["poblacion_edad_jubilatoria"],"extension":["csv"],"analista":["Rafael Rofman & Ximena de la Fuente"],"fuentes":["R449C290"],"cambio_nombre_output":{},"cambio_nombre_cols":{},"aclaraciones":{},"control":{"check_columnas":{"cols_nuevas":[],"cols_faltantes":[]},"comparacion_clases":[{"columna":"anio","clase_previa":"numeric","clase_nueva":"integer","coinciden":false},{"columna":"anio","clase_previa":"numeric","clase_nueva":"integer","coinciden":false},{"columna":"categoria","clase_previa":"character","clase_nueva":"glue","coinciden":false},{"columna":"categoria","clase_previa":"character","clase_nueva":"character","coinciden":true},{"columna":"poblacion","clase_previa":"numeric","clase_nueva":"numeric","coinciden":true},{"columna":"poblacion","clase_previa":"numeric","clase_nueva":"numeric","coinciden":true}],"diferencia_nfilas":[0],"comparacion_cols":{"poblacion":{"nuevos_na":[0],"mean_variaciones_rel":[0],"ks_test":[1],"mw_test":[1],"tasa_posibles_outliers":[0],"filas_nuevos_na":[],"filas_posibles_outliers":[]}}},"exportar":[true],"pk":["anio","categoria"],"es_serie_tiempo":[true],"columna_indice_tiempo":{},"max_tiempo":{},"columna_geo_referencia":{},"nivel_agregacion":{},"nullables":[""],"descripcion_columnas":{"anio":["Año de referencia"],"categoria":["Varones (de 65 años) y Mujeres (de 60) en edad jubilatoria"],"poblacion":["Habitantes"]},"unidades":{"poblacion":["unidades"]},"classes":{"anio":["integer"],"categoria":["glue","character"],"poblacion":["numeric"]},"data":[{"anio":1950,"categoria":"Varones de 65 años","poblacion":38677},{"anio":1951,"categoria":"Varones de 65 años","poblacion":40752},{"anio":1952,"categoria":"Varones de 65 años","poblacion":43062},{"anio":1953,"categoria":"Varones de 65 años","poblacion":45321},{"anio":1954,"categoria":"Varones de 65 años","poblacion":47169},{"anio":1955,"categoria":"Varones de 65 años","poblacion":48661},{"anio":1956,"categoria":"Varones de 65 años","poblacion":50030},{"anio":1957,"categoria":"Varones de 65 años","poblacion":51574},{"anio":1958,"categoria":"Varones de 65 años","poblacion":52961},{"anio":1959,"categoria":"Varones de 65 años","poblacion":54543},{"anio":1960,"categoria":"Varones de 65 años","poblacion":56083},{"anio":1961,"categoria":"Varones de 65 años","poblacion":57749},{"anio":1962,"categoria":"Varones de 65 años","poblacion":59241},{"anio":1963,"categoria":"Varones de 65 años","poblacion":60735},{"anio":1964,"categoria":"Varones de 65 años","poblacion":62580},{"anio":1965,"categoria":"Varones de 65 años","poblacion":64759},{"anio":1966,"categoria":"Varones de 65 años","poblacion":66775},{"anio":1967,"categoria":"Varones de 65 años","poblacion":68957},{"anio":1968,"categoria":"Varones de 65 años","poblacion":71035},{"anio":1969,"categoria":"Varones de 65 años","poblacion":72743},{"anio":1970,"categoria":"Varones de 65 años","poblacion":73988},{"anio":1971,"categoria":"Varones de 65 años","poblacion":75414},{"anio":1972,"categoria":"Varones de 65 años","poblacion":76340},{"anio":1973,"categoria":"Varones de 65 años","poblacion":77210},{"anio":1974,"categoria":"Varones de 65 años","poblacion":78089},{"anio":1975,"categoria":"Varones de 65 años","poblacion":78941},{"anio":1976,"categoria":"Varones de 65 años","poblacion":79968},{"anio":1977,"categoria":"Varones de 65 años","poblacion":81180},{"anio":1978,"categoria":"Varones de 65 años","poblacion":82727},{"anio":1979,"categoria":"Varones de 65 años","poblacion":83967},{"anio":1980,"categoria":"Varones de 65 años","poblacion":84836},{"anio":1981,"categoria":"Varones de 65 años","poblacion":85984},{"anio":1982,"categoria":"Varones de 65 años","poblacion":86519},{"anio":1983,"categoria":"Varones de 65 años","poblacion":87166},{"anio":1984,"categoria":"Varones de 65 años","poblacion":88796},{"anio":1985,"categoria":"Varones de 65 años","poblacion":91015},{"anio":1986,"categoria":"Varones de 65 años","poblacion":93040},{"anio":1987,"categoria":"Varones de 65 años","poblacion":95248},{"anio":1988,"categoria":"Varones de 65 años","poblacion":97623},{"anio":1989,"categoria":"Varones de 65 años","poblacion":99886},{"anio":1990,"categoria":"Varones de 65 años","poblacion":101781},{"anio":1991,"categoria":"Varones de 65 años","poblacion":103502},{"anio":1992,"categoria":"Varones de 65 años","poblacion":105645},{"anio":1993,"categoria":"Varones de 65 años","poblacion":107532},{"anio":1994,"categoria":"Varones de 65 años","poblacion":108652},{"anio":1995,"categoria":"Varones de 65 años","poblacion":109146},{"anio":1996,"categoria":"Varones de 65 años","poblacion":109637},{"anio":1997,"categoria":"Varones de 65 años","poblacion":110275},{"anio":1998,"categoria":"Varones de 65 años","poblacion":111019},{"anio":1999,"categoria":"Varones de 65 años","poblacion":111782},{"anio":2000,"categoria":"Varones de 65 años","poblacion":112665},{"anio":2001,"categoria":"Varones de 65 años","poblacion":113752},{"anio":2002,"categoria":"Varones de 65 años","poblacion":114592},{"anio":2003,"categoria":"Varones de 65 años","poblacion":115560},{"anio":2004,"categoria":"Varones de 65 años","poblacion":117099},{"anio":2005,"categoria":"Varones de 65 años","poblacion":119667},{"anio":2006,"categoria":"Varones de 65 años","poblacion":122540},{"anio":2007,"categoria":"Varones de 65 años","poblacion":125795},{"anio":2008,"categoria":"Varones de 65 años","poblacion":129150},{"anio":2009,"categoria":"Varones de 65 años","poblacion":132898},{"anio":2010,"categoria":"Varones de 65 años","poblacion":136997},{"anio":2011,"categoria":"Varones de 65 años","poblacion":141279},{"anio":2012,"categoria":"Varones de 65 años","poblacion":145768},{"anio":2013,"categoria":"Varones de 65 años","poblacion":150400},{"anio":2014,"categoria":"Varones de 65 años","poblacion":153880},{"anio":2015,"categoria":"Varones de 65 años","poblacion":155607},{"anio":2016,"categoria":"Varones de 65 años","poblacion":159286},{"anio":2017,"categoria":"Varones de 65 años","poblacion":162546},{"anio":2018,"categoria":"Varones de 65 años","poblacion":165767},{"anio":2019,"categoria":"Varones de 65 años","poblacion":168505},{"anio":2020,"categoria":"Varones de 65 años","poblacion":170791},{"anio":2021,"categoria":"Varones de 65 años","poblacion":172680},{"anio":2022,"categoria":"Varones de 65 años","poblacion":174244},{"anio":2023,"categoria":"Varones de 65 años","poblacion":175843},{"anio":1950,"categoria":"Mujeres de 60 años","poblacion":49418},{"anio":1951,"categoria":"Mujeres de 60 años","poblacion":51041},{"anio":1952,"categoria":"Mujeres de 60 años","poblacion":52479},{"anio":1953,"categoria":"Mujeres de 60 años","poblacion":54013},{"anio":1954,"categoria":"Mujeres de 60 años","poblacion":55983},{"anio":1955,"categoria":"Mujeres de 60 años","poblacion":58499},{"anio":1956,"categoria":"Mujeres de 60 años","poblacion":60923},{"anio":1957,"categoria":"Mujeres de 60 años","poblacion":63401},{"anio":1958,"categoria":"Mujeres de 60 años","poblacion":65889},{"anio":1959,"categoria":"Mujeres de 60 años","poblacion":68470},{"anio":1960,"categoria":"Mujeres de 60 años","poblacion":70997},{"anio":1961,"categoria":"Mujeres de 60 años","poblacion":73520},{"anio":1962,"categoria":"Mujeres de 60 años","poblacion":76246},{"anio":1963,"categoria":"Mujeres de 60 años","poblacion":78938},{"anio":1964,"categoria":"Mujeres de 60 años","poblacion":81440},{"anio":1965,"categoria":"Mujeres de 60 años","poblacion":83715},{"anio":1966,"categoria":"Mujeres de 60 años","poblacion":86178},{"anio":1967,"categoria":"Mujeres de 60 años","poblacion":88343},{"anio":1968,"categoria":"Mujeres de 60 años","poblacion":90527},{"anio":1969,"categoria":"Mujeres de 60 años","poblacion":93498},{"anio":1970,"categoria":"Mujeres de 60 años","poblacion":96881},{"anio":1971,"categoria":"Mujeres de 60 años","poblacion":99861},{"anio":1972,"categoria":"Mujeres de 60 años","poblacion":103192},{"anio":1973,"categoria":"Mujeres de 60 años","poblacion":106384},{"anio":1974,"categoria":"Mujeres de 60 años","poblacion":108633},{"anio":1975,"categoria":"Mujeres de 60 años","poblacion":109719},{"anio":1976,"categoria":"Mujeres de 60 años","poblacion":111403},{"anio":1977,"categoria":"Mujeres de 60 años","poblacion":112477},{"anio":1978,"categoria":"Mujeres de 60 años","poblacion":113704},{"anio":1979,"categoria":"Mujeres de 60 años","poblacion":115823},{"anio":1980,"categoria":"Mujeres de 60 años","poblacion":119099},{"anio":1981,"categoria":"Mujeres de 60 años","poblacion":122100},{"anio":1982,"categoria":"Mujeres de 60 años","poblacion":124856},{"anio":1983,"categoria":"Mujeres de 60 años","poblacion":127559},{"anio":1984,"categoria":"Mujeres de 60 años","poblacion":130289},{"anio":1985,"categoria":"Mujeres de 60 años","poblacion":132979},{"anio":1986,"categoria":"Mujeres de 60 años","poblacion":135204},{"anio":1987,"categoria":"Mujeres de 60 años","poblacion":138384},{"anio":1988,"categoria":"Mujeres de 60 años","poblacion":140914},{"anio":1989,"categoria":"Mujeres de 60 años","poblacion":142017},{"anio":1990,"categoria":"Mujeres de 60 años","poblacion":141214},{"anio":1991,"categoria":"Mujeres de 60 años","poblacion":140667},{"anio":1992,"categoria":"Mujeres de 60 años","poblacion":139697},{"anio":1993,"categoria":"Mujeres de 60 años","poblacion":139173},{"anio":1994,"categoria":"Mujeres de 60 años","poblacion":139086},{"anio":1995,"categoria":"Mujeres de 60 años","poblacion":140068},{"anio":1996,"categoria":"Mujeres de 60 años","poblacion":141249},{"anio":1997,"categoria":"Mujeres de 60 años","poblacion":142307},{"anio":1998,"categoria":"Mujeres de 60 años","poblacion":143638},{"anio":1999,"categoria":"Mujeres de 60 años","poblacion":145445},{"anio":2000,"categoria":"Mujeres de 60 años","poblacion":148039},{"anio":2001,"categoria":"Mujeres de 60 años","poblacion":151044},{"anio":2002,"categoria":"Mujeres de 60 años","poblacion":154386},{"anio":2003,"categoria":"Mujeres de 60 años","poblacion":158182},{"anio":2004,"categoria":"Mujeres de 60 años","poblacion":162183},{"anio":2005,"categoria":"Mujeres de 60 años","poblacion":166452},{"anio":2006,"categoria":"Mujeres de 60 años","poblacion":170993},{"anio":2007,"categoria":"Mujeres de 60 años","poblacion":175799},{"anio":2008,"categoria":"Mujeres de 60 años","poblacion":180822},{"anio":2009,"categoria":"Mujeres de 60 años","poblacion":184106},{"anio":2010,"categoria":"Mujeres de 60 años","poblacion":184923},{"anio":2011,"categoria":"Mujeres de 60 años","poblacion":189574},{"anio":2012,"categoria":"Mujeres de 60 años","poblacion":192745},{"anio":2013,"categoria":"Mujeres de 60 años","poblacion":195383},{"anio":2014,"categoria":"Mujeres de 60 años","poblacion":197799},{"anio":2015,"categoria":"Mujeres de 60 años","poblacion":199541},{"anio":2016,"categoria":"Mujeres de 60 años","poblacion":201675},{"anio":2017,"categoria":"Mujeres de 60 años","poblacion":204038},{"anio":2018,"categoria":"Mujeres de 60 años","poblacion":205279},{"anio":2019,"categoria":"Mujeres de 60 años","poblacion":205038},{"anio":2020,"categoria":"Mujeres de 60 años","poblacion":209491},{"anio":2021,"categoria":"Mujeres de 60 años","poblacion":210869},{"anio":2022,"categoria":"Mujeres de 60 años","poblacion":211201},{"anio":2023,"categoria":"Mujeres de 60 años","poblacion":213789}]}
