{"subtopico":["SALING"],"output_name":["ISA_composicion-ipcf_it3"],"extension":["csv"],"analista":[""],"fuentes":["R165C0"],"cambio_nombre_output":{},"cambio_nombre_cols":{},"aclaraciones":["Participación de las distintas fuentes en el ingreso familiar total. Por edad del jefe, 2024"],"control":{"check_columnas":{"cols_nuevas":[],"cols_faltantes":[]},"comparacion_clases":[{"columna":"year","clase_previa":"numeric","clase_nueva":"numeric","coinciden":true},{"columna":"semestre","clase_previa":"numeric","clase_nueva":"numeric","coinciden":true},{"columna":"edad_jefe","clase_previa":"character","clase_nueva":"character","coinciden":true},{"columna":"fuente","clase_previa":"character","clase_nueva":"character","coinciden":true},{"columna":"proporcion","clase_previa":"numeric","clase_nueva":"numeric","coinciden":true}],"diferencia_nfilas":[0],"comparacion_cols":{"proporcion":{"nuevos_na":[0],"mean_variaciones_rel":[0],"ks_test":[1],"mw_test":[1],"tasa_posibles_outliers":[0],"filas_nuevos_na":[],"filas_posibles_outliers":[]}}},"exportar":[true],"pk":["year","semestre","edad_jefe","fuente"],"es_serie_tiempo":[true],"columna_indice_tiempo":["year","semestre"],"columna_geo_referencia":{},"nivel_agregacion":["pais"],"nullables":[""],"descripcion_columnas":{"year":["Año calendario"],"semestre":["Semestre"],"edad_jefe":["Grupo etario al que pertenece el jefe de hogar"],"fuente":["Fuente de ingreso"],"proporcion":["Proporción representada por las distintas fuentes de ingreso en el ingreso total"]},"unidades":{"proporcion":["porcentaje"]},"classes":{"year":["numeric"],"semestre":["numeric"],"edad_jefe":["character"],"fuente":["character"],"proporcion":["numeric"]},"data":[{"year":2023,"semestre":1,"edad_jefe":"24 o menos","fuente":"Ingreso laboral","proporcion":0.7148},{"year":2023,"semestre":1,"edad_jefe":"25 a 34","fuente":"Ingreso laboral","proporcion":0.8637},{"year":2023,"semestre":1,"edad_jefe":"35 a 44","fuente":"Ingreso laboral","proporcion":0.906},{"year":2023,"semestre":1,"edad_jefe":"45 a 54","fuente":"Ingreso laboral","proporcion":0.898},{"year":2023,"semestre":1,"edad_jefe":"55 a 64","fuente":"Ingreso laboral","proporcion":0.7904},{"year":2023,"semestre":1,"edad_jefe":"65 o mas","fuente":"Ingreso laboral","proporcion":0.4152},{"year":2023,"semestre":1,"edad_jefe":"24 o menos","fuente":"Ingreso de capital","proporcion":0.0097},{"year":2023,"semestre":1,"edad_jefe":"25 a 34","fuente":"Ingreso de capital","proporcion":0.0098},{"year":2023,"semestre":1,"edad_jefe":"35 a 44","fuente":"Ingreso de capital","proporcion":0.0084},{"year":2023,"semestre":1,"edad_jefe":"45 a 54","fuente":"Ingreso de capital","proporcion":0.0115},{"year":2023,"semestre":1,"edad_jefe":"55 a 64","fuente":"Ingreso de capital","proporcion":0.0237},{"year":2023,"semestre":1,"edad_jefe":"65 o mas","fuente":"Ingreso de capital","proporcion":0.0158},{"year":2023,"semestre":1,"edad_jefe":"24 o menos","fuente":"Ingreso de jubilaciones","proporcion":0.0271},{"year":2023,"semestre":1,"edad_jefe":"25 a 34","fuente":"Ingreso de jubilaciones","proporcion":0.0192},{"year":2023,"semestre":1,"edad_jefe":"35 a 44","fuente":"Ingreso de jubilaciones","proporcion":0.027},{"year":2023,"semestre":1,"edad_jefe":"45 a 54","fuente":"Ingreso de jubilaciones","proporcion":0.0475},{"year":2023,"semestre":1,"edad_jefe":"55 a 64","fuente":"Ingreso de jubilaciones","proporcion":0.1598},{"year":2023,"semestre":1,"edad_jefe":"65 o mas","fuente":"Ingreso de jubilaciones","proporcion":0.5405},{"year":2023,"semestre":1,"edad_jefe":"24 o menos","fuente":"Ingreso de transferencias estatales","proporcion":0.0722},{"year":2023,"semestre":1,"edad_jefe":"25 a 34","fuente":"Ingreso de transferencias estatales","proporcion":0.0728},{"year":2023,"semestre":1,"edad_jefe":"35 a 44","fuente":"Ingreso de transferencias estatales","proporcion":0.0425},{"year":2023,"semestre":1,"edad_jefe":"45 a 54","fuente":"Ingreso de transferencias estatales","proporcion":0.0218},{"year":2023,"semestre":1,"edad_jefe":"55 a 64","fuente":"Ingreso de transferencias estatales","proporcion":0.0172},{"year":2023,"semestre":1,"edad_jefe":"65 o mas","fuente":"Ingreso de transferencias estatales","proporcion":0.0143},{"year":2023,"semestre":1,"edad_jefe":"24 o menos","fuente":"Otros ingresos","proporcion":0.1763},{"year":2023,"semestre":1,"edad_jefe":"25 a 34","fuente":"Otros ingresos","proporcion":0.0346},{"year":2023,"semestre":1,"edad_jefe":"35 a 44","fuente":"Otros ingresos","proporcion":0.0161},{"year":2023,"semestre":1,"edad_jefe":"45 a 54","fuente":"Otros ingresos","proporcion":0.0212},{"year":2023,"semestre":1,"edad_jefe":"55 a 64","fuente":"Otros ingresos","proporcion":0.0091},{"year":2023,"semestre":1,"edad_jefe":"65 o mas","fuente":"Otros ingresos","proporcion":0.0141}]}
