{"subtopico":["SALING"],"output_name":["ISA_regiones-ipcf_it1"],"extension":["csv"],"analista":[""],"fuentes":["R174C0"],"cambio_nombre_output":{},"cambio_nombre_cols":{},"aclaraciones":["Ingreso per c치pita familiar relativo al promedio nacional, 2024"],"control":{"check_columnas":{"cols_nuevas":[],"cols_faltantes":[]},"comparacion_clases":[{"columna":"year","clase_previa":"numeric","clase_nueva":"numeric","coinciden":true},{"columna":"semestre","clase_previa":"numeric","clase_nueva":"numeric","coinciden":true},{"columna":"region","clase_previa":"character","clase_nueva":"character","coinciden":true},{"columna":"deflactor","clase_previa":"character","clase_nueva":"character","coinciden":true},{"columna":"indice","clase_previa":"numeric","clase_nueva":"numeric","coinciden":true}],"diferencia_nfilas":[0],"comparacion_cols":{"indice":{"nuevos_na":[0],"mean_variaciones_rel":[0],"ks_test":[1],"mw_test":[1],"tasa_posibles_outliers":[0],"filas_nuevos_na":[],"filas_posibles_outliers":[]}}},"exportar":[true],"pk":["year","semestre","region","deflactor"],"es_serie_tiempo":[true],"columna_indice_tiempo":["year","semestre"],"columna_geo_referencia":{},"nivel_agregacion":["regiones"],"nullables":[""],"descripcion_columnas":{"year":["A침o calendario"],"semestre":["Semestre"],"region":["Regi칩n geogr치fica"],"deflactor":["Deflactor usado para los ingresos"],"indice":["Valor relativo del ingreso regional respecto al nacional en 2023-I"]},"unidades":{"indice":["unidades"]},"classes":{"year":["numeric"],"semestre":["numeric"],"region":["character"],"deflactor":["character"],"indice":["numeric"]},"data":[{"year":2023,"semestre":1,"region":"Partidos del GBA","deflactor":"ipc","indice":0.9407},{"year":2023,"semestre":1,"region":"CABA","deflactor":"ipc","indice":1.6315},{"year":2023,"semestre":1,"region":"Pampeana","deflactor":"ipc","indice":0.9972},{"year":2023,"semestre":1,"region":"NEA","deflactor":"ipc","indice":0.7166},{"year":2023,"semestre":1,"region":"NOA","deflactor":"ipc","indice":0.7067},{"year":2023,"semestre":1,"region":"Cuyo","deflactor":"ipc","indice":0.8455},{"year":2023,"semestre":1,"region":"Patagonia","deflactor":"ipc","indice":1.3026},{"year":2023,"semestre":1,"region":"Partidos del GBA","deflactor":"linea de pobreza","indice":0.9242},{"year":2023,"semestre":1,"region":"CABA","deflactor":"linea de pobreza","indice":1.6021},{"year":2023,"semestre":1,"region":"Pampeana","deflactor":"linea de pobreza","indice":0.9856},{"year":2023,"semestre":1,"region":"NEA","deflactor":"linea de pobreza","indice":0.833},{"year":2023,"semestre":1,"region":"NOA","deflactor":"linea de pobreza","indice":0.8567},{"year":2023,"semestre":1,"region":"Cuyo","deflactor":"linea de pobreza","indice":0.8668},{"year":2023,"semestre":1,"region":"Patagonia","deflactor":"linea de pobreza","indice":1.0809}]}
