{"subtopico":["SALING"],"output_name":["ISA_edad_genero_i3"],"extension":["csv"],"analista":[""],"fuentes":["R170C0"],"cambio_nombre_output":{},"cambio_nombre_cols":{},"aclaraciones":["Evolución de salario real por grupos etarios y género en términos reales. 1992 -2024"],"control":{"check_columnas":{"cols_nuevas":[],"cols_faltantes":[]},"comparacion_clases":[{"columna":"ano","clase_previa":"numeric","clase_nueva":"numeric","coinciden":true},{"columna":"variable","clase_previa":"character","clase_nueva":"character","coinciden":true},{"columna":"valor","clase_previa":"numeric","clase_nueva":"numeric","coinciden":true}],"diferencia_nfilas":[5],"comparacion_cols":{"valor":{"nuevos_na":[0],"mean_variaciones_rel":[0.0016],"ks_test":[1],"mw_test":[0.9725],"tasa_posibles_outliers":[0.025],"filas_nuevos_na":[],"filas_posibles_outliers":[{"ano":2023,"variable":"Hombres","valor.x":10525,"valor.y":10008.6479,"variaciones_rel":-0.0491,"zscaled_variaciones_rel":-5.0045},{"ano":2023,"variable":"(15-24)","valor.x":5624,"valor.y":5107.0485,"variaciones_rel":-0.0919,"zscaled_variaciones_rel":-9.4719},{"ano":2023,"variable":"(25-64)","valor.x":9945,"valor.y":9538.3918,"variaciones_rel":-0.0409,"zscaled_variaciones_rel":-4.1525},{"ano":2023,"variable":"(65 +)","valor.x":7553,"valor.y":7856.477,"variaciones_rel":0.0402,"zscaled_variaciones_rel":4.2974}]}}},"exportar":[true],"pk":["ano","variable"],"es_serie_tiempo":[true],"columna_indice_tiempo":["ano"],"columna_geo_referencia":{},"nivel_agregacion":["pais"],"nullables":[""],"descripcion_columnas":{"ano":["Año calendario"],"variable":["Variable considerada: ingreso laboral mensual en términos reales de todos los trabajadores captados por la EPH por género y grupo etario"],"valor":["Valor que toma la variable considerada"]},"unidades":{"valor":["unidades"]},"classes":{"ano":["numeric"],"variable":["character"],"valor":["numeric"]},"data":[{"ano":1992,"variable":"Mujeres","valor":11177.5541},{"ano":1992,"variable":"Hombres","valor":15652.0543},{"ano":1992,"variable":"(15-24)","valor":9325.0493},{"ano":1992,"variable":"(25-64)","valor":15413.8854},{"ano":1992,"variable":"(65 +)","valor":10078.0859},{"ano":1993,"variable":"Mujeres","valor":11434.3935},{"ano":1993,"variable":"Hombres","valor":16048.7482},{"ano":1993,"variable":"(15-24)","valor":9611.7935},{"ano":1993,"variable":"(25-64)","valor":15752.7325},{"ano":1993,"variable":"(65 +)","valor":10661.4478},{"ano":1994,"variable":"Mujeres","valor":11960.3274},{"ano":1994,"variable":"Hombres","valor":15935.7736},{"ano":1994,"variable":"(15-24)","valor":9519.5858},{"ano":1994,"variable":"(25-64)","valor":15891.9977},{"ano":1994,"variable":"(65 +)","valor":11594.9351},{"ano":1995,"variable":"Mujeres","valor":11135.0664},{"ano":1995,"variable":"Hombres","valor":16145.9725},{"ano":1995,"variable":"(15-24)","valor":8704.0652},{"ano":1995,"variable":"(25-64)","valor":15773.7655},{"ano":1995,"variable":"(65 +)","valor":11322.8618},{"ano":1996,"variable":"Mujeres","valor":10991.3449},{"ano":1996,"variable":"Hombres","valor":15551.7456},{"ano":1996,"variable":"(15-24)","valor":8237.2197},{"ano":1996,"variable":"(25-64)","valor":15295.978},{"ano":1996,"variable":"(65 +)","valor":12881.3285},{"ano":1997,"variable":"Mujeres","valor":11203.3057},{"ano":1997,"variable":"Hombres","valor":15304.5133},{"ano":1997,"variable":"(15-24)","valor":8261.7954},{"ano":1997,"variable":"(25-64)","valor":15159.5902},{"ano":1997,"variable":"(65 +)","valor":12287.5208},{"ano":1998,"variable":"Mujeres","valor":11367.5086},{"ano":1998,"variable":"Hombres","valor":16448.8004},{"ano":1998,"variable":"(15-24)","valor":8220.2981},{"ano":1998,"variable":"(25-64)","valor":15853.473},{"ano":1998,"variable":"(65 +)","valor":16611.9921},{"ano":1999,"variable":"Mujeres","valor":11185.6111},{"ano":1999,"variable":"Hombres","valor":15587.4877},{"ano":1999,"variable":"(15-24)","valor":7966.9001},{"ano":1999,"variable":"(25-64)","valor":15201.6736},{"ano":1999,"variable":"(65 +)","valor":13189.0976},{"ano":2000,"variable":"Mujeres","valor":11055.5836},{"ano":2000,"variable":"Hombres","valor":15219.1569},{"ano":2000,"variable":"(15-24)","valor":7560.6772},{"ano":2000,"variable":"(25-64)","valor":14885.4026},{"ano":2000,"variable":"(65 +)","valor":11759.4126},{"ano":2001,"variable":"Mujeres","valor":10849.7113},{"ano":2001,"variable":"Hombres","valor":14551.9534},{"ano":2001,"variable":"(15-24)","valor":6861.1805},{"ano":2001,"variable":"(25-64)","valor":14362.161},{"ano":2001,"variable":"(65 +)","valor":11638.1292},{"ano":2002,"variable":"Mujeres","valor":7865.4248},{"ano":2002,"variable":"Hombres","valor":10695.2648},{"ano":2002,"variable":"(15-24)","valor":5009.7062},{"ano":2002,"variable":"(25-64)","valor":10439.1474},{"ano":2002,"variable":"(65 +)","valor":9141.5092},{"ano":2003,"variable":"Mujeres","valor":7562.2076},{"ano":2003,"variable":"Hombres","valor":10422.16},{"ano":2003,"variable":"(15-24)","valor":4850.6727},{"ano":2003,"variable":"(25-64)","valor":10062.846},{"ano":2003,"variable":"(65 +)","valor":9461.1793},{"ano":2004,"variable":"Mujeres","valor":7970.8887},{"ano":2004,"variable":"Hombres","valor":10695.2971},{"ano":2004,"variable":"(15-24)","valor":5140.9742},{"ano":2004,"variable":"(25-64)","valor":10491.7735},{"ano":2004,"variable":"(65 +)","valor":8919.2352},{"ano":2005,"variable":"Mujeres","valor":9022.4154},{"ano":2005,"variable":"Hombres","valor":11853.5248},{"ano":2005,"variable":"(15-24)","valor":6041.2372},{"ano":2005,"variable":"(25-64)","valor":11664.6371},{"ano":2005,"variable":"(65 +)","valor":9691.8075},{"ano":2006,"variable":"Mujeres","valor":9967.229},{"ano":2006,"variable":"Hombres","valor":12973.6941},{"ano":2006,"variable":"(15-24)","valor":6538.2444},{"ano":2006,"variable":"(25-64)","valor":12782.9276},{"ano":2006,"variable":"(65 +)","valor":10688.3622},{"ano":2007,"variable":"Mujeres","valor":9630.5233},{"ano":2007,"variable":"Hombres","valor":13529.5032},{"ano":2007,"variable":"(15-24)","valor":7105.2403},{"ano":2007,"variable":"(25-64)","valor":12926.6856},{"ano":2007,"variable":"(65 +)","valor":10746.7516},{"ano":2008,"variable":"Mujeres","valor":9766.8896},{"ano":2008,"variable":"Hombres","valor":13125.0688},{"ano":2008,"variable":"(15-24)","valor":7238.6428},{"ano":2008,"variable":"(25-64)","valor":12619.4811},{"ano":2008,"variable":"(65 +)","valor":9909.8556},{"ano":2009,"variable":"Mujeres","valor":10455.5301},{"ano":2009,"variable":"Hombres","valor":13366.7343},{"ano":2009,"variable":"(15-24)","valor":7311.5842},{"ano":2009,"variable":"(25-64)","valor":12956.3515},{"ano":2009,"variable":"(65 +)","valor":11480.0111},{"ano":2010,"variable":"Mujeres","valor":10436.9763},{"ano":2010,"variable":"Hombres","valor":13565.9853},{"ano":2010,"variable":"(15-24)","valor":7456.7221},{"ano":2010,"variable":"(25-64)","valor":13067.2636},{"ano":2010,"variable":"(65 +)","valor":11921.8742},{"ano":2011,"variable":"Mujeres","valor":11218.148},{"ano":2011,"variable":"Hombres","valor":14488.502},{"ano":2011,"variable":"(15-24)","valor":8033.0215},{"ano":2011,"variable":"(25-64)","valor":13988.4096},{"ano":2011,"variable":"(65 +)","valor":11792.4709},{"ano":2012,"variable":"Mujeres","valor":11115.4796},{"ano":2012,"variable":"Hombres","valor":14010.2591},{"ano":2012,"variable":"(15-24)","valor":7996.5581},{"ano":2012,"variable":"(25-64)","valor":13634.7039},{"ano":2012,"variable":"(65 +)","valor":11739.2691},{"ano":2013,"variable":"Mujeres","valor":11158.1582},{"ano":2013,"variable":"Hombres","valor":14297.7916},{"ano":2013,"variable":"(15-24)","valor":8267.6504},{"ano":2013,"variable":"(25-64)","valor":13750.2681},{"ano":2013,"variable":"(65 +)","valor":12180.9214},{"ano":2014,"variable":"Mujeres","valor":10259.7946},{"ano":2014,"variable":"Hombres","valor":13110.234},{"ano":2014,"variable":"(15-24)","valor":7422.0772},{"ano":2014,"variable":"(25-64)","valor":12591.9834},{"ano":2014,"variable":"(65 +)","valor":12303.4145},{"ano":2015,"variable":"Mujeres","valor":10690.4946},{"ano":2015,"variable":"Hombres","valor":13218.5962},{"ano":2015,"variable":"(15-24)","valor":7926.249},{"ano":2015,"variable":"(25-64)","valor":12833.8021},{"ano":2015,"variable":"(65 +)","valor":11453.6964},{"ano":2016,"variable":"Mujeres","valor":10460.3157},{"ano":2016,"variable":"Hombres","valor":13195.9601},{"ano":2016,"variable":"(15-24)","valor":7164.9948},{"ano":2016,"variable":"(25-64)","valor":12677.9255},{"ano":2016,"variable":"(65 +)","valor":13037.1381},{"ano":2017,"variable":"Mujeres","valor":10745.8501},{"ano":2017,"variable":"Hombres","valor":13656.5051},{"ano":2017,"variable":"(15-24)","valor":7193.3339},{"ano":2017,"variable":"(25-64)","valor":13245.2217},{"ano":2017,"variable":"(65 +)","valor":11682.4671},{"ano":2018,"variable":"Mujeres","valor":9503.6059},{"ano":2018,"variable":"Hombres","valor":12441.2164},{"ano":2018,"variable":"(15-24)","valor":6538.2669},{"ano":2018,"variable":"(25-64)","valor":11788.4726},{"ano":2018,"variable":"(65 +)","valor":11428.7595},{"ano":2019,"variable":"Mujeres","valor":8818.8111},{"ano":2019,"variable":"Hombres","valor":11516.2373},{"ano":2019,"variable":"(15-24)","valor":5708.8257},{"ano":2019,"variable":"(25-64)","valor":11004.5271},{"ano":2019,"variable":"(65 +)","valor":9540.7281},{"ano":2020,"variable":"Mujeres","valor":8375.3911},{"ano":2020,"variable":"Hombres","valor":10276.1587},{"ano":2020,"variable":"(15-24)","valor":4882.302},{"ano":2020,"variable":"(25-64)","valor":9921.7246},{"ano":2020,"variable":"(65 +)","valor":9902.7386},{"ano":2021,"variable":"Mujeres","valor":8601.5407},{"ano":2021,"variable":"Hombres","valor":11061.405},{"ano":2021,"variable":"(15-24)","valor":5377.3083},{"ano":2021,"variable":"(25-64)","valor":10565.3288},{"ano":2021,"variable":"(65 +)","valor":9540.7837},{"ano":2022,"variable":"Mujeres","valor":8066.011},{"ano":2022,"variable":"Hombres","valor":10159.0029},{"ano":2022,"variable":"(15-24)","valor":5190.6753},{"ano":2022,"variable":"(25-64)","valor":9787.1247},{"ano":2022,"variable":"(65 +)","valor":8391.9281},{"ano":2023,"variable":"Mujeres","valor":7723.0918},{"ano":2023,"variable":"Hombres","valor":10008.6479},{"ano":2023,"variable":"(15-24)","valor":5107.0485},{"ano":2023,"variable":"(25-64)","valor":9538.3918},{"ano":2023,"variable":"(65 +)","valor":7856.477},{"ano":2024,"variable":"Mujeres","valor":6693.5593},{"ano":2024,"variable":"Hombres","valor":8873.8167},{"ano":2024,"variable":"(15-24)","valor":4567.8515},{"ano":2024,"variable":"(25-64)","valor":8376.7024},{"ano":2024,"variable":"(65 +)","valor":6876.8861}]}
