{"subtopico":["COMEXT"],"output_name":["exportaciones_servicios_top_20_destinos"],"extension":["csv"],"analista":[""],"fuentes":["R158C0"],"aclaraciones":[""],"control":["no se incluyeron controles"],"exportar":[true],"pk":["descripcionpais","year"],"es_serie_tiempo":[false],"columna_indice_tiempo":[false],"columna_geo_referencia":["iso3"],"nivel_agregacion":["continente (region)"],"nullables":[""],"etiquetas_indicadores":{"export_value_pc":["Exportaciones de servicios (% del total exportado en servicios)"],"export_value_pc.1":["Exportaciones de servicios (% del total exportado en servicios)"]},"unidades":{"export_value_pc":["porcentaje"]},"classes":{"year":["integer"],"iso3":["character"],"descripcionpais":["character"],"export_value_pc":["numeric"]},"data":[{"year":2015,"iso3":"DEU","descripcionpais":"Alemania","export_value_pc":1.8162},{"year":2015,"iso3":"BOL","descripcionpais":"Bolivia","export_value_pc":2.9207},{"year":2015,"iso3":"BRA","descripcionpais":"Brasil","export_value_pc":9.5471},{"year":2015,"iso3":"BEL","descripcionpais":"Bélgica","export_value_pc":1.6095},{"year":2015,"iso3":"CHL","descripcionpais":"Chile","export_value_pc":7.2755},{"year":2015,"iso3":"COL","descripcionpais":"Colombia","export_value_pc":0.9138},{"year":2015,"iso3":"KOR","descripcionpais":"Corea del Sur","export_value_pc":0.7178},{"year":2015,"iso3":"ESP","descripcionpais":"España","export_value_pc":1.7613},{"year":2015,"iso3":"USA","descripcionpais":"Estados Unidos","export_value_pc":21.1263},{"year":2015,"iso3":"FRA","descripcionpais":"Francia","export_value_pc":1.2998},{"year":2015,"iso3":"GRC","descripcionpais":"Grecia","export_value_pc":0.7079},{"year":2015,"iso3":"IRL","descripcionpais":"Irlanda","export_value_pc":1.0176},{"year":2015,"iso3":"MEX","descripcionpais":"México","export_value_pc":1.2838},{"year":2015,"iso3":"PRY","descripcionpais":"Paraguay","export_value_pc":4.4547},{"year":2015,"iso3":"NLD","descripcionpais":"Países Bajos","export_value_pc":1.7094},{"year":2015,"iso3":"PER","descripcionpais":"Perú","export_value_pc":0.8208},{"year":2015,"iso3":"GBR","descripcionpais":"Reino Unido","export_value_pc":2.1579},{"year":2015,"iso3":"","descripcionpais":"Resto","export_value_pc":31.8894},{"year":2015,"iso3":"SGP","descripcionpais":"Singapur","export_value_pc":0.7399},{"year":2015,"iso3":"CHE","descripcionpais":"Suiza","export_value_pc":1.4943},{"year":2015,"iso3":"URY","descripcionpais":"Uruguay","export_value_pc":4.7362},{"year":2016,"iso3":"DEU","descripcionpais":"Alemania","export_value_pc":3.0379},{"year":2016,"iso3":"BOL","descripcionpais":"Bolivia","export_value_pc":2.5323},{"year":2016,"iso3":"BRA","descripcionpais":"Brasil","export_value_pc":8.9538},{"year":2016,"iso3":"BEL","descripcionpais":"Bélgica","export_value_pc":1.5377},{"year":2016,"iso3":"CHL","descripcionpais":"Chile","export_value_pc":6.7643},{"year":2016,"iso3":"CHN","descripcionpais":"China","export_value_pc":1.1281},{"year":2016,"iso3":"COL","descripcionpais":"Colombia","export_value_pc":2.0995},{"year":2016,"iso3":"KOR","descripcionpais":"Corea del Sur","export_value_pc":1.7372},{"year":2016,"iso3":"ESP","descripcionpais":"España","export_value_pc":4.5291},{"year":2016,"iso3":"USA","descripcionpais":"Estados Unidos","export_value_pc":26.7888},{"year":2016,"iso3":"FRA","descripcionpais":"Francia","export_value_pc":2.4423},{"year":2016,"iso3":"ITA","descripcionpais":"Italia","export_value_pc":2.05},{"year":2016,"iso3":"JPN","descripcionpais":"Japón","export_value_pc":1.0891},{"year":2016,"iso3":"MEX","descripcionpais":"México","export_value_pc":2.14},{"year":2016,"iso3":"PRY","descripcionpais":"Paraguay","export_value_pc":4.8966},{"year":2016,"iso3":"NLD","descripcionpais":"Países Bajos","export_value_pc":1.849},{"year":2016,"iso3":"PER","descripcionpais":"Perú","export_value_pc":2.5376},{"year":2016,"iso3":"GBR","descripcionpais":"Reino Unido","export_value_pc":3.3777},{"year":2016,"iso3":"","descripcionpais":"Resto","export_value_pc":14.3695},{"year":2016,"iso3":"CHE","descripcionpais":"Suiza","export_value_pc":1.705},{"year":2016,"iso3":"URY","descripcionpais":"Uruguay","export_value_pc":4.4345},{"year":2017,"iso3":"DEU","descripcionpais":"Alemania","export_value_pc":3.1634},{"year":2017,"iso3":"BOL","descripcionpais":"Bolivia","export_value_pc":2.1046},{"year":2017,"iso3":"BRA","descripcionpais":"Brasil","export_value_pc":9.4634},{"year":2017,"iso3":"BEL","descripcionpais":"Bélgica","export_value_pc":1.5167},{"year":2017,"iso3":"CHL","descripcionpais":"Chile","export_value_pc":5.737},{"year":2017,"iso3":"CHN","descripcionpais":"China","export_value_pc":1.2665},{"year":2017,"iso3":"COL","descripcionpais":"Colombia","export_value_pc":2.3129},{"year":2017,"iso3":"KOR","descripcionpais":"Corea del Sur","export_value_pc":2.1176},{"year":2017,"iso3":"ESP","descripcionpais":"España","export_value_pc":4.3542},{"year":2017,"iso3":"USA","descripcionpais":"Estados Unidos","export_value_pc":29.594},{"year":2017,"iso3":"FRA","descripcionpais":"Francia","export_value_pc":2.3182},{"year":2017,"iso3":"IRL","descripcionpais":"Irlanda","export_value_pc":1.0288},{"year":2017,"iso3":"ITA","descripcionpais":"Italia","export_value_pc":1.9504},{"year":2017,"iso3":"MEX","descripcionpais":"México","export_value_pc":2.3541},{"year":2017,"iso3":"PRY","descripcionpais":"Paraguay","export_value_pc":4.5991},{"year":2017,"iso3":"NLD","descripcionpais":"Países Bajos","export_value_pc":2.3515},{"year":2017,"iso3":"PER","descripcionpais":"Perú","export_value_pc":2.601},{"year":2017,"iso3":"GBR","descripcionpais":"Reino Unido","export_value_pc":3.65},{"year":2017,"iso3":"","descripcionpais":"Resto","export_value_pc":11.5131},{"year":2017,"iso3":"CHE","descripcionpais":"Suiza","export_value_pc":1.6682},{"year":2017,"iso3":"URY","descripcionpais":"Uruguay","export_value_pc":4.3352},{"year":2018,"iso3":"DEU","descripcionpais":"Alemania","export_value_pc":3.3504},{"year":2018,"iso3":"BOL","descripcionpais":"Bolivia","export_value_pc":1.925},{"year":2018,"iso3":"BRA","descripcionpais":"Brasil","export_value_pc":9.8251},{"year":2018,"iso3":"BEL","descripcionpais":"Bélgica","export_value_pc":1.2673},{"year":2018,"iso3":"CHL","descripcionpais":"Chile","export_value_pc":5.9989},{"year":2018,"iso3":"CHN","descripcionpais":"China","export_value_pc":1.4781},{"year":2018,"iso3":"COL","descripcionpais":"Colombia","export_value_pc":2.383},{"year":2018,"iso3":"KOR","descripcionpais":"Corea del Sur","export_value_pc":2.0376},{"year":2018,"iso3":"ESP","descripcionpais":"España","export_value_pc":4.4865},{"year":2018,"iso3":"USA","descripcionpais":"Estados Unidos","export_value_pc":27.6966},{"year":2018,"iso3":"FRA","descripcionpais":"Francia","export_value_pc":2.2063},{"year":2018,"iso3":"IRL","descripcionpais":"Irlanda","export_value_pc":1.1645},{"year":2018,"iso3":"ITA","descripcionpais":"Italia","export_value_pc":1.8597},{"year":2018,"iso3":"MEX","descripcionpais":"México","export_value_pc":2.3447},{"year":2018,"iso3":"PRY","descripcionpais":"Paraguay","export_value_pc":4.3138},{"year":2018,"iso3":"NLD","descripcionpais":"Países Bajos","export_value_pc":2.2993},{"year":2018,"iso3":"PER","descripcionpais":"Perú","export_value_pc":2.4087},{"year":2018,"iso3":"GBR","descripcionpais":"Reino Unido","export_value_pc":3.867},{"year":2018,"iso3":"","descripcionpais":"Resto","export_value_pc":13.072},{"year":2018,"iso3":"CHE","descripcionpais":"Suiza","export_value_pc":1.8301},{"year":2018,"iso3":"URY","descripcionpais":"Uruguay","export_value_pc":4.1853},{"year":2019,"iso3":"DEU","descripcionpais":"Alemania","export_value_pc":3.3284},{"year":2019,"iso3":"BOL","descripcionpais":"Bolivia","export_value_pc":2.0723},{"year":2019,"iso3":"BRA","descripcionpais":"Brasil","export_value_pc":10.5882},{"year":2019,"iso3":"BEL","descripcionpais":"Bélgica","export_value_pc":1.1758},{"year":2019,"iso3":"CHL","descripcionpais":"Chile","export_value_pc":6.022},{"year":2019,"iso3":"CHN","descripcionpais":"China","export_value_pc":1.6193},{"year":2019,"iso3":"COL","descripcionpais":"Colombia","export_value_pc":2.2998},{"year":2019,"iso3":"KOR","descripcionpais":"Corea del Sur","export_value_pc":1.2664},{"year":2019,"iso3":"ESP","descripcionpais":"España","export_value_pc":3.8986},{"year":2019,"iso3":"USA","descripcionpais":"Estados Unidos","export_value_pc":26.7323},{"year":2019,"iso3":"FRA","descripcionpais":"Francia","export_value_pc":2.4687},{"year":2019,"iso3":"IRL","descripcionpais":"Irlanda","export_value_pc":1.434},{"year":2019,"iso3":"ITA","descripcionpais":"Italia","export_value_pc":2.0947},{"year":2019,"iso3":"MEX","descripcionpais":"México","export_value_pc":2.4238},{"year":2019,"iso3":"PRY","descripcionpais":"Paraguay","export_value_pc":4.3966},{"year":2019,"iso3":"NLD","descripcionpais":"Países Bajos","export_value_pc":2.3025},{"year":2019,"iso3":"PER","descripcionpais":"Perú","export_value_pc":2.3665},{"year":2019,"iso3":"GBR","descripcionpais":"Reino Unido","export_value_pc":3.4783},{"year":2019,"iso3":"","descripcionpais":"Resto","export_value_pc":13.6748},{"year":2019,"iso3":"CHE","descripcionpais":"Suiza","export_value_pc":2.2787},{"year":2019,"iso3":"URY","descripcionpais":"Uruguay","export_value_pc":4.0784},{"year":2020,"iso3":"DEU","descripcionpais":"Alemania","export_value_pc":3.4195},{"year":2020,"iso3":"BOL","descripcionpais":"Bolivia","export_value_pc":1.7284},{"year":2020,"iso3":"BRA","descripcionpais":"Brasil","export_value_pc":6.3883},{"year":2020,"iso3":"BEL","descripcionpais":"Bélgica","export_value_pc":2.0175},{"year":2020,"iso3":"CHL","descripcionpais":"Chile","export_value_pc":5.3413},{"year":2020,"iso3":"CHN","descripcionpais":"China","export_value_pc":1.1916},{"year":2020,"iso3":"COL","descripcionpais":"Colombia","export_value_pc":1.5445},{"year":2020,"iso3":"KOR","descripcionpais":"Corea del Sur","export_value_pc":1.3584},{"year":2020,"iso3":"ESP","descripcionpais":"España","export_value_pc":2.6032},{"year":2020,"iso3":"USA","descripcionpais":"Estados Unidos","export_value_pc":34.1833},{"year":2020,"iso3":"FRA","descripcionpais":"Francia","export_value_pc":1.841},{"year":2020,"iso3":"IRL","descripcionpais":"Irlanda","export_value_pc":2.6786},{"year":2020,"iso3":"ITA","descripcionpais":"Italia","export_value_pc":1.1597},{"year":2020,"iso3":"MEX","descripcionpais":"México","export_value_pc":2.2131},{"year":2020,"iso3":"PRY","descripcionpais":"Paraguay","export_value_pc":3.3005},{"year":2020,"iso3":"NLD","descripcionpais":"Países Bajos","export_value_pc":2.4086},{"year":2020,"iso3":"PER","descripcionpais":"Perú","export_value_pc":1.2043},{"year":2020,"iso3":"GBR","descripcionpais":"Reino Unido","export_value_pc":3.7033},{"year":2020,"iso3":"","descripcionpais":"Resto","export_value_pc":14.4508},{"year":2020,"iso3":"CHE","descripcionpais":"Suiza","export_value_pc":2.7403},{"year":2020,"iso3":"URY","descripcionpais":"Uruguay","export_value_pc":4.5239},{"year":2021,"iso3":"DEU","descripcionpais":"Alemania","export_value_pc":2.4406},{"year":2021,"iso3":"BRA","descripcionpais":"Brasil","export_value_pc":6.7063},{"year":2021,"iso3":"BEL","descripcionpais":"Bélgica","export_value_pc":2.1846},{"year":2021,"iso3":"CAN","descripcionpais":"Canadá","export_value_pc":1.2992},{"year":2021,"iso3":"CHL","descripcionpais":"Chile","export_value_pc":4.7682},{"year":2021,"iso3":"CHN","descripcionpais":"China","export_value_pc":1.28},{"year":2021,"iso3":"COL","descripcionpais":"Colombia","export_value_pc":1.4582},{"year":2021,"iso3":"KOR","descripcionpais":"Corea del Sur","export_value_pc":1.4304},{"year":2021,"iso3":"DNK","descripcionpais":"Dinamarca","export_value_pc":1.2768},{"year":2021,"iso3":"ESP","descripcionpais":"España","export_value_pc":2.4619},{"year":2021,"iso3":"USA","descripcionpais":"Estados Unidos","export_value_pc":34.6699},{"year":2021,"iso3":"FRA","descripcionpais":"Francia","export_value_pc":1.4742},{"year":2021,"iso3":"IRL","descripcionpais":"Irlanda","export_value_pc":4.1036},{"year":2021,"iso3":"MEX","descripcionpais":"México","export_value_pc":3.4796},{"year":2021,"iso3":"PRY","descripcionpais":"Paraguay","export_value_pc":2.3755},{"year":2021,"iso3":"NLD","descripcionpais":"Países Bajos","export_value_pc":2.1419},{"year":2021,"iso3":"GBR","descripcionpais":"Reino Unido","export_value_pc":5.1991},{"year":2021,"iso3":"","descripcionpais":"Resto","export_value_pc":12.6105},{"year":2021,"iso3":"SGP","descripcionpais":"Singapur","export_value_pc":1.2875},{"year":2021,"iso3":"CHE","descripcionpais":"Suiza","export_value_pc":3.3868},{"year":2021,"iso3":"URY","descripcionpais":"Uruguay","export_value_pc":3.9649},{"year":2022,"iso3":"DEU","descripcionpais":"Alemania","export_value_pc":2.1529},{"year":2022,"iso3":"BOL","descripcionpais":"Bolivia","export_value_pc":1.2598},{"year":2022,"iso3":"BRA","descripcionpais":"Brasil","export_value_pc":10.4089},{"year":2022,"iso3":"BEL","descripcionpais":"Bélgica","export_value_pc":1.8622},{"year":2022,"iso3":"CAN","descripcionpais":"Canadá","export_value_pc":1.1259},{"year":2022,"iso3":"CHL","descripcionpais":"Chile","export_value_pc":5.6269},{"year":2022,"iso3":"CHN","descripcionpais":"China","export_value_pc":1.0813},{"year":2022,"iso3":"COL","descripcionpais":"Colombia","export_value_pc":1.8719},{"year":2022,"iso3":"KOR","descripcionpais":"Corea del Sur","export_value_pc":1.2975},{"year":2022,"iso3":"ESP","descripcionpais":"España","export_value_pc":3.1457},{"year":2022,"iso3":"USA","descripcionpais":"Estados Unidos","export_value_pc":30.167},{"year":2022,"iso3":"FRA","descripcionpais":"Francia","export_value_pc":1.7674},{"year":2022,"iso3":"IRL","descripcionpais":"Irlanda","export_value_pc":2.6367},{"year":2022,"iso3":"MEX","descripcionpais":"México","export_value_pc":2.9191},{"year":2022,"iso3":"PRY","descripcionpais":"Paraguay","export_value_pc":3.6065},{"year":2022,"iso3":"NLD","descripcionpais":"Países Bajos","export_value_pc":1.7855},{"year":2022,"iso3":"PER","descripcionpais":"Perú","export_value_pc":1.4341},{"year":2022,"iso3":"GBR","descripcionpais":"Reino Unido","export_value_pc":4.6349},{"year":2022,"iso3":"","descripcionpais":"Resto","export_value_pc":13.3322},{"year":2022,"iso3":"CHE","descripcionpais":"Suiza","export_value_pc":2.5649},{"year":2022,"iso3":"URY","descripcionpais":"Uruguay","export_value_pc":5.3188}]}
